fedfind/__init__.py
fedfind/cli.py
fedfind/const.py
fedfind/exceptions.py
fedfind/helpers.py
fedfind/release.py
fedfind-6.1.3.dist-info/licenses/COPYING
fedfind-6.1.3.dist-info/METADATA
fedfind-6.1.3.dist-info/WHEEL
fedfind-6.1.3.dist-info/entry_points.txt
fedfind-6.1.3.dist-info/top_level.txt
fedfind-6.1.3.dist-info/RECORD
