Metadata-Version: 2.4
Name: fedfind
Version: 6.1.3
Summary: Fedora Finder finds Fedora - images, more to come?
Home-page: https://forge.fedoraproject.org/quality/fedfind
Author: Adam Williamson
Author-email: awilliam@redhat.com
License: GPLv3+
Keywords: fedora release image media iso
Classifier: Development Status :: 5 - Production/Stable
Classifier: Topic :: Utilities
Classifier: License :: OSI Approved :: GNU General Public License v3 or later (GPLv3+)
License-File: COPYING
Requires-Dist: cached-property; python_version < "3.8"
Requires-Dist: productmd
Requires-Dist: setuptools
Requires-Dist: six
Dynamic: author
Dynamic: author-email
Dynamic: classifier
Dynamic: description
Dynamic: description-content-type
Dynamic: home-page
Dynamic: keywords
Dynamic: license
Dynamic: license-file
Dynamic: requires-dist
Dynamic: summary
